[
  {
    "partido": "Hellas Verona - Cremonese",
    "liga": "Serie A",
    "hora": "12:30 p. m.",
    "canal": "Star +"
  },
  {
    "partido": "Bolognia - Atalanta",
    "liga": "Serie A",
    "hora": "2:45 p. m.",
    "canal": "Star +"
  },
  {
    "partido": "Athletic Club - Osasuna",
    "liga": "Liga de Espana",
    "hora": "3:00 p. m.",
    "canal": "Directv 610"
  },
  {
    "partido": "Oxford United - Arsenal",
    "liga": "FA Cup",
    "hora": "3:00 p. m.",
    "canal": "ESPN y Star+"
  },
  {
    "partido": "Pachuca - Puebla",
    "liga": "Liga de México",
    "hora": "10:10 p. m.",
    "canal": "Claro Sports"
  }
]