[
  {
    "partido": "Fiorentina - Real Betis",
    "liga": "Conference League",
    "hora": "2:00 p. m.",
    "canal": "Disney+"
  },
  {
    "partido": "Manchester United - Athletic Club",
    "liga": "Liga de Europa",
    "hora": "2:00 p. m.",
    "canal": "ESPN / Disney+"
  },
  {
    "partido": "Chelsea - Djurgardens",
    "liga": "Conference League",
    "hora": "2:00 p. m.",
    "canal": "Disney+"
  },
  {
    "partido": "Bodo Glimt - Tottenham Hotspur",
    "liga": "Liga de Europa",
    "hora": "2:00 p. m.",
    "canal": "ESPN 2 / Disney+"
  },
  {
    "partido": "Vélez Sarsfield - Olimpia",
    "liga": "Copa Libertadores",
    "hora": "5:00 p. m.",
    "canal": "ESPN / Disney+"
  },
  {
    "partido": "D. Iquique - Atlético Mineiro",
    "liga": "Copa Sudamericana",
    "hora": "5:00 p. m.",
    "canal": "ESPN 5 / Disney+"
  },
  {
    "partido": "Talleres de Córdoba - Libertad",
    "liga": "Copa Libertadores",
    "hora": "5:00 p. m.",
    "canal": "ESPN 2 / Disney+"
  },
  {
    "partido": "Racing - Huracán",
    "liga": "Copa Sudamericana",
    "hora": "5:00 p. m.",
    "canal": "Directv 610"
  },
  {
    "partido": "San José - Fluminense",
    "liga": "Copa Sudamericana",
    "hora": "7:30 p. m.",
    "canal": "Directv 610"
  },
  {
    "partido": "Barcelona (ECU) - River Plate",
    "liga": "Copa Libertadores",
    "hora": "7:30 p. m.",
    "canal": "ESPN 2 / Disney+"
  },
  {
    "partido": "Atlético Nacional - Internacional",
    "liga": "Copa Libertadores",
    "hora": "7:30 p. m.",
    "canal": "ESPN / Disney+"
  },
  {
    "partido": "Millonarios - Pereira",
    "liga": "Liga BetPlay",
    "hora": "7:30 p. m.",
    "canal": "Win Sports+"
  },
  {
    "partido": "Universitario - Independiente",
    "liga": "Copa Libertadores",
    "hora": "9:00 p. m.",
    "canal": "ESPN 7 / Disney+"
  },
  {
    "partido": "Cienciano - Caracas F.C",
    "liga": "Copa Sudamericana",
    "hora": "9:00 p. m.",
    "canal": "ESPN 5 / Disney+"
  }
]