[
  {
    "partido": "Ucrania - España",
    "liga": "Mundial Sub-20 Chile",
    "hora": "2:30 p. m.",
    "canal": "Directv 610"
  },
  {
    "partido": "Envigado F.C - Pereira",
    "liga": "Copa Betplay",
    "hora": "3:00 p. m.",
    "canal": "Win Sports"
  },
  {
    "partido": "Real Cundinamarca - Orsomarso",
    "liga": "Torneo Betplay",
    "hora": "5:10 p. m.",
    "canal": "Win Sports +"
  },
  {
    "partido": "Chile - México",
    "liga": "Mundial Sub-20 Chile",
    "hora": "6:00 p. m.",
    "canal": "Directv 610"
  },
  {
    "partido": "Millonarios - América",
    "liga": "Liga BetPlay",
    "hora": "7:30 p. m.",
    "canal": "Win Sports+"
  }
]