[
  {
    "partido": "Athletic Club - Osasuna",
    "liga": "Copa del Rey",
    "hora": "1:30 p. m.",
    "canal": "Directv 612"
  },
  {
    "partido": "Real Sociedad - Rayo Vallecano",
    "liga": "Copa del Rey",
    "hora": "1:30 p. m.",
    "canal": "Directv 613"
  },
  {
    "partido": "Ipswich Town - Brighton & Hove",
    "liga": "Liga de Inglaterra",
    "hora": "2:30 p. m.",
    "canal": "ESPN 3 / Disney+"
  },
  {
    "partido": "Manchester United - Southampton",
    "liga": "Liga de Inglaterra",
    "hora": "3:00 p. m.",
    "canal": "ESPN / Disney+"
  },
  {
    "partido": "Real Madrid - Celta de Vigo",
    "liga": "Copa del Rey",
    "hora": "3:30 p. m.",
    "canal": "Directv 610"
  },
  {
    "partido": "Millonarios - Melgar",
    "liga": "Partido amistoso",
    "hora": "7:00 p. m.",
    "canal": "Disney+"
  }
]