[
  {
    "partido": "Hellas Verona - Parma",
    "liga": "Serie A",
    "hora": "6:30 a. m.",
    "canal": "ESPN / Disney+"
  },
  {
    "partido": "Real Oviedo - Rayo Vallecano",
    "liga": "Liga de España",
    "hora": "8:00 a. m.",
    "canal": "ESPN 2 / Disney+"
  },
  {
    "partido": "Cremonese - Roma",
    "liga": "Serie A",
    "hora": "9:00 a. m.",
    "canal": "Disney+"
  },
  {
    "partido": "Leeds - Aston Villa",
    "liga": "Liga de Inglaterra",
    "hora": "9:00 a. m.",
    "canal": "ESPN / Disney+"
  },
  {
    "partido": "Real Betis - Girona",
    "liga": "Liga de España",
    "hora": "10:15 a. m.",
    "canal": "Disney+"
  },
  {
    "partido": "Arsenal - Tottenham Hotspur",
    "liga": "Liga de Inglaterra",
    "hora": "11:30 a. m.",
    "canal": "Disney+"
  },
  {
    "partido": "St. Pauli - Union Berlin",
    "liga": "Bundesliga",
    "hora": "11:30 a. m.",
    "canal": "ESPN 2 / Disney+"
  },
  {
    "partido": "Lazio - Lecce",
    "liga": "Serie A",
    "hora": "12:00 p. m.",
    "canal": "Disney+"
  },
  {
    "partido": "Getafe - Atlético de Madrid",
    "liga": "Liga de España",
    "hora": "12:30 p. m.",
    "canal": "ESPN / Disney+"
  },
  {
    "partido": "Lille - Paris FC",
    "liga": "Liga de Francia",
    "hora": "2:45 p. m.",
    "canal": "ESPN 2 / Disney+"
  },
  {
    "partido": "Inter - Milán",
    "liga": "Serie A",
    "hora": "2:45 p. m.",
    "canal": "ESPN / Disney+"
  },
  {
    "partido": "Elche - Real Madrid",
    "liga": "Liga de España",
    "hora": "3:00 p. m.",
    "canal": "Disney+"
  },
  {
    "partido": "Independiente Medellín - Atlético Nacional",
    "liga": "Liga BetPlay",
    "hora": "5:45 p. m.",
    "canal": "Win Sports+"
  },
  {
    "partido": "Boca Juniors - CA Talleres",
    "liga": "Superliga Argentina",
    "hora": "6:00 p. m.",
    "canal": "ESPN / Disney+"
  },
  {
    "partido": "América - Junior",
    "liga": "Liga BetPlay",
    "hora": "8:00 p. m.",
    "canal": "Win Sports / Win Sports+"
  }
]