[
  {
    "partido": "Real Madrid - Manchester City",
    "liga": "Champions League",
    "hora": "2:00 p. m.",
    "canal": "ESPN / Star +"
  },
  {
    "partido": "Arsenal - Bayern Munich",
    "liga": "Champions League",
    "hora": "2:00 p. m.",
    "canal": "ESPN 2 / Star +"
  },
  {
    "partido": "Corinthians - Nacional (Par)",
    "liga": "Copa Sudamericana",
    "hora": "5:00 p. m.",
    "canal": "ESPN 3 / Star +"
  },
  {
    "partido": "Argentinos Juniors - Racing",
    "liga": "Copa Sudamericana",
    "hora": "5:00 p. m.",
    "canal": "ESPN 2 / Star +"
  },
  {
    "partido": "Estudiantes - The Strongest",
    "liga": "Copa Libertadores",
    "hora": "5:00 p. m.",
    "canal": "ESPN / Star +"
  },
  {
    "partido": "Gremio - Huachipato",
    "liga": "Copa Libertadores",
    "hora": "5:00 p. m.",
    "canal": "ESPN 5 / Star +"
  },
  {
    "partido": "Fortaleza F.C - Once Caldas",
    "liga": "Copa Betplay",
    "hora": "6:00 p. m.",
    "canal": "Win Sports +"
  },
  {
    "partido": "Colombia Femenino - Guatemala",
    "liga": "Amistoso femenino",
    "hora": "6:30 p. m.",
    "canal": "Caracol HD2 / Golcaracol.com"
  },
  {
    "partido": "Libertad - Deportivo Táchira",
    "liga": "Copa Libertadores",
    "hora": "7:00 p. m.",
    "canal": "ESPN / Star +"
  },
  {
    "partido": "Fluminense - Colo Colo",
    "liga": "Copa Libertadores",
    "hora": "7:00 p. m.",
    "canal": "ESPN 5 / Star +"
  },
  {
    "partido": "Boca Juniors - Sportivo Trinidense",
    "liga": "Copa Sudamericana",
    "hora": "7:00 p. m.",
    "canal": "ESPN / Star +"
  },
  {
    "partido": "Danubio - Sportivo Ameliano",
    "liga": "Copa Sudamericana",
    "hora": "7:30 p. m.",
    "canal": "Directv 610"
  },
  {
    "partido": "Atlético Paranaense - Rayo Zuliano",
    "liga": "Copa Sudamericana",
    "hora": "7:30 p. m.",
    "canal": "ESPN 3 / Star +"
  },
  {
    "partido": "Pereira - Leones",
    "liga": "Copa Betplay",
    "hora": "8:00 p. m.",
    "canal": "Win Sports +"
  },
  {
    "partido": "Junior - Universitario",
    "liga": "Copa Libertadores",
    "hora": "9:00 p. m.",
    "canal": "ESPN / Star +"
  }
]