[
  {
    "partido": "Empoli - Napoli",
    "liga": "Serie A",
    "hora": "5:30 a. m.",
    "canal": "ESPN / Disney+"
  },
  {
    "partido": "Mallorca - Rayo Vallecano",
    "liga": "Liga de Espana",
    "hora": "7:00 a. m.",
    "canal": "DSports"
  },
  {
    "partido": "Venezia - Atalanta",
    "liga": "Serie A",
    "hora": "8:00 a. m.",
    "canal": "ESPN 3 / Disney+"
  },
  {
    "partido": "Lecce - Fiorentina",
    "liga": "Serie A",
    "hora": "8:00 a. m.",
    "canal": "Disney+"
  },
  {
    "partido": "Wolverhampton - Manchester City",
    "liga": "Liga de Inglaterra",
    "hora": "8:00 a. m.",
    "canal": "ESPN / Disney+"
  },
  {
    "partido": "Atlético de Madrid - Leganés",
    "liga": "Liga de Espana",
    "hora": "9:15 a. m.",
    "canal": "ESPN 2 / Disney+"
  },
  {
    "partido": "Nantes - Niza",
    "liga": "Liga de Francia",
    "hora": "10:00 a. m.",
    "canal": "ESPN 4 / Disney+"
  },
  {
    "partido": "Liverpool - Chelsea",
    "liga": "Liga de Inglaterra",
    "hora": "10:30 a. m.",
    "canal": "Disney+"
  },
  {
    "partido": "Cagliari - Torino",
    "liga": "Serie A",
    "hora": "11:00 a. m.",
    "canal": "Disney+"
  },
  {
    "partido": "Villarreal - Getafe",
    "liga": "Liga de Espana",
    "hora": "11:30 a. m.",
    "canal": "ESPN / Disney+"
  },
  {
    "partido": "Roma - Inter",
    "liga": "Serie A",
    "hora": "1:45 p. m.",
    "canal": "ESPN / Disney+"
  },
  {
    "partido": "Barcelona - Sevilla",
    "liga": "Liga de Espana",
    "hora": "2:00 p. m.",
    "canal": "DSports"
  },
  {
    "partido": "Japón Femenino - Brasil Femenino",
    "liga": "Mundial femenino Sub-17",
    "hora": "3:00 p. m.",
    "canal": "DSports"
  },
  {
    "partido": "Equidad - América",
    "liga": "Liga BetPlay",
    "hora": "3:45 p. m.",
    "canal": "Win Sports+"
  },
  {
    "partido": "Junior - Pereira",
    "liga": "Liga BetPlay",
    "hora": "5:45 p. m.",
    "canal": "Win Sports / Win Sports+"
  },
  {
    "partido": "Inglaterra Femenino - México",
    "liga": "Mundial femenino Sub-17",
    "hora": "6:00 p. m.",
    "canal": "DSports"
  },
  {
    "partido": "Águilas Doradas - Bucaramanga",
    "liga": "Liga BetPlay",
    "hora": "8:00 p. m.",
    "canal": "Win Sports / Win Sports+"
  }
]